MANIFEST.in
README.md
setup.py
awsfabrictasks/__init__.py
awsfabrictasks/conf.py
awsfabrictasks/decorators.py
awsfabrictasks/default_settings.py
awsfabrictasks/hostslist.py
awsfabrictasks/main.py
awsfabrictasks/regions.py
awsfabrictasks/ubuntu.py
awsfabrictasks/utils.py
awsfabrictasks.egg-info/PKG-INFO
awsfabrictasks.egg-info/SOURCES.txt
awsfabrictasks.egg-info/dependency_links.txt
awsfabrictasks.egg-info/entry_points.txt
awsfabrictasks.egg-info/requires.txt
awsfabrictasks.egg-info/top_level.txt
awsfabrictasks.egg-info/zip-safe
awsfabrictasks/awsenv/__init__.py
awsfabrictasks/awsenv/api.py
awsfabrictasks/awsenv/tasks.py
awsfabrictasks/ec2/__init__.py
awsfabrictasks/ec2/api.py
awsfabrictasks/ec2/tasks.py
awsfabrictasks/rds/__init__.py
awsfabrictasks/rds/api.py
awsfabrictasks/rds/tasks.py
awsfabrictasks/s3/__init__.py
awsfabrictasks/s3/api.py
awsfabrictasks/s3/tasks.py
awsfabrictasks/tests/__init__.py
awsfabrictasks/tests/test_utils.py
awsfabrictasks/tests/ec2/__init__.py
awsfabrictasks/tests/ec2/test_api.py
awsfabrictasks/tests/s3/__init__.py
awsfabrictasks/tests/s3/test_api.py