Metadata-Version: 1.0
Name: awsfabrictasks
Version: 1.1.1
Summary: Fabric tasks for Amazon Web Services.
Home-page: https://github.com/espenak/awsfabrictasks
Author: Espen Angell Kristiansen
Author-email: UNKNOWN
License: BSD
Platform: UNKNOWN
Classifier: Intended Audience :: Developers
Classifier: License :: OSI Approved
Classifier: Programming Language :: Python
